{
  "month": "jan",
  "day": 20,
  "holidays": [
    {
      "title": "National Cheese Lover&#39;s Day",
      "description": null
    },
    {
      "title": "National DJ Day",
      "description": null
    },
    {
      "title": "National Penguin Day",
      "description": null
    },
    {
      "title": "Camcorder Day",
      "description": null
    },
    {
      "title": "Guru Gobind Singh Jayanti",
      "description": null
    },
    {
      "title": "Inauguration Day",
      "description": null
    },
    {
      "title": "International Day of Acceptance",
      "description": null
    },
    {
      "title": "National Claudia Day",
      "description": null
    },
    {
      "title": "National Coffee Break Day",
      "description": null
    },
    {
      "title": "National Sebastian Day",
      "description": null
    },
    {
      "title": "Penguin Awareness Day",
      "description": null
    },
    {
      "title": "Rid the World of Fad Diets &amp; Gimmicks Day",
      "description": null
    },
    {
      "title": "Take A Walk Outdoors Day",
      "description": null
    }
  ]
}
