{
  "month": "may",
  "day": 27,
  "holidays": [
    {
      "title": "Memorial Day",
      "description": null
    },
    {
      "title": "National Hairstylist Mental Health Awareness Day",
      "description": "Hairstylists so often lend a friendly ear to their customers — this observation is all about offering yours in return."
    },
    {
      "title": "National Sunscreen Day",
      "description": "Rub and absorb that lotion, cream, or spray before enjoying the warmth and light of summer."
    },
    {
      "title": "Asher day",
      "description": "Despite its historical and biblical origins, the name Asher wasn’t well known until the 1980s."
    },
    {
      "title": "Cheese Rolling Gloucester",
      "description": "Ready, set, go! It is time to experience the Cheese Rolling Gloucester!"
    },
    {
      "title": "Decoration Day",
      "description": "Bring out the flowers, flags, and red poppies to commemorate the fallen on this day."
    },
    {
      "title": "National Aaron Day",
      "description": "Let’s find out about the name Aaron, its history, popularity, and origins."
    },
    {
      "title": "National Cellophane Tape Day",
      "description": "Time to commemorate the invention of one of the most practical things i.e., cellophane tape."
    },
    {
      "title": "National Grape Popsicle Day",
      "description": "Beat the heat and tickle those taste buds with this refreshing pop."
    },
    {
      "title": "National Gray Day",
      "description": "Raise your voices and spread awareness about brain cancer with our information."
    },
    {
      "title": "National Jordan Day",
      "description": "The name Jordan is an intriguing one. This National Jordan Day, let’s find out why."
    },
    {
      "title": "Nothing to Fear Day",
      "description": "Fear not; come and join us as we celebrate Nothing To Fear Day."
    },
    {
      "title": "Old Time Player Piano Day",
      "description": "Old-Time Player Piano Day takes place to memorialize this unique musical instrument that plays itself."
    },
    {
      "title": "Prayer for Peace Memorial Day",
      "description": "Honor the brave American soldiers who died in the military this Prayer for Peace Memorial Day."
    },
    {
      "title": "Slavery Abolition Day (Guadeloupe)",
      "description": "This Slavery Abolition Day, join us as we uncover Guadeloupe’s complex history!"
    },
    {
      "title": "Spring Bank Holiday",
      "description": "A day for the general population in the U.K. to kick back and relax."
    },
    {
      "title": "Sunscreen Day",
      "description": "Making sunscreen a priority, and protecting the largest organ of the body at all costs."
    },
    {
      "title": "Blippi’s Birthday",
      "description": "This children’s character is loved by many and is the source of many good childhood memories."
    },
    {
      "title": "Jadakiss’s Birthday",
      "description": "This rapper has enviable talent and the global recognition to prove it."
    },
    {
      "title": "Princess Mae’s Birthday",
      "description": "This Instagram star has had a glimpse of stardom, and she’s not turning back."
    },
    {
      "title": "Royalty Brown’s Birthday",
      "description": "This celebrity family member has it made — with a hip-hop dad and model mom, she’s set for life!"
    },
    {
      "title": "Ryan Henry’s Birthday",
      "description": "For this talented tattoo artist and reality T.V. star, the sky really is the limit."
    },
    {
      "title": "Zach Herron’s Birthday",
      "description": "With his melodious voice and dashing looks, Zach Herron has captivated the hearts of millions worldwide."
    }
  ]
}
