{
  "month": "apr",
  "day": 24,
  "holidays": [
    {
      "title": "National Arbor Day",
      "description": null
    },
    {
      "title": "Action Day for Tolerance and Respect between People",
      "description": null
    },
    {
      "title": "Armenian Genocide Remembrance Day",
      "description": null
    },
    {
      "title": "Coronation Day of Pope Benedict XVI",
      "description": null
    },
    {
      "title": "Fashion Revolution Day",
      "description": null
    },
    {
      "title": "International Day of Multilateralism and Diplomacy for Peace",
      "description": null
    },
    {
      "title": "National Brandon Day",
      "description": null
    },
    {
      "title": "National Hairball Awareness Day",
      "description": null
    },
    {
      "title": "National Pet Care for All Day",
      "description": null
    },
    {
      "title": "National Pigs in a Blanket Day",
      "description": null
    },
    {
      "title": "National Skipping Day",
      "description": null
    },
    {
      "title": "New Kids on the Block Day",
      "description": null
    },
    {
      "title": "Scream Day",
      "description": null
    },
    {
      "title": "Undiagnosed Children&#39;s Awareness Day",
      "description": null
    },
    {
      "title": "World Day for Animals in Laboratories",
      "description": null
    },
    {
      "title": "World Women’s Wellness Day",
      "description": null
    }
  ]
}
