{
  "month": "feb",
  "day": 20,
  "holidays": [
    {
      "title": "National Love Your Pet Day",
      "description": null
    },
    {
      "title": "Clean Out Your Bookcase Day",
      "description": null
    },
    {
      "title": "Hoodie Hoo Day",
      "description": null
    },
    {
      "title": "Mizoram State Day",
      "description": null
    },
    {
      "title": "National Caregivers Day",
      "description": null
    },
    {
      "title": "National Cherry Pie Day",
      "description": null
    },
    {
      "title": "National Comfy Day",
      "description": null
    },
    {
      "title": "National Day of Solidarity with Muslim Arab and South Asian Immigrants",
      "description": null
    },
    {
      "title": "National Handcuff Day",
      "description": null
    },
    {
      "title": "National Leadership Day",
      "description": null
    },
    {
      "title": "National Muffin Day",
      "description": null
    },
    {
      "title": "National Student Volunteer Day",
      "description": null
    },
    {
      "title": "National Tartar Sauce Day",
      "description": null
    },
    {
      "title": "National Whistleblower Reward Day",
      "description": null
    },
    {
      "title": "No One Eats Alone Day",
      "description": null
    },
    {
      "title": "No Politics Day",
      "description": null
    },
    {
      "title": "Statehood Day of Arunachal Pradesh",
      "description": null
    },
    {
      "title": "Women in Blue Jeans Days",
      "description": null
    },
    {
      "title": "World Day of Social Justice",
      "description": null
    },
    {
      "title": "Yukon Heritage Day",
      "description": null
    }
  ]
}
