{
  "month": "oct",
  "day": 12,
  "holidays": [
    {
      "title": "Farmers Day",
      "description": null
    },
    {
      "title": "Day of Respect For Cultural Diversity",
      "description": null
    },
    {
      "title": "Día de la Raza",
      "description": null
    },
    {
      "title": "Equatorial Guinea Independence Day",
      "description": null
    },
    {
      "title": "Harry Potter Book Day",
      "description": null
    },
    {
      "title": "Hispanic Day",
      "description": null
    },
    {
      "title": "Hoshana Rabbah",
      "description": null
    },
    {
      "title": "Indigenous Resistance Day",
      "description": null
    },
    {
      "title": "Indigenous Resistance Day in Venezuela",
      "description": null
    },
    {
      "title": "Lady of Aparecida",
      "description": null
    },
    {
      "title": "Mexico: Day of the Pluricultural Nation",
      "description": null
    },
    {
      "title": "National Freethought Day",
      "description": null
    },
    {
      "title": "National Gumbo Day",
      "description": null
    },
    {
      "title": "National Pulled Pork Day",
      "description": null
    },
    {
      "title": "National Savings Day",
      "description": null
    },
    {
      "title": "National Vermont Day",
      "description": null
    },
    {
      "title": "Our Lady of Aparecida&#39;s Day",
      "description": null
    },
    {
      "title": "Pastor Appreciation Day",
      "description": null
    },
    {
      "title": "Uruguay Day of Cultural Diversity/Day of the Races",
      "description": null
    },
    {
      "title": "White Sunday",
      "description": null
    },
    {
      "title": "World Arthritis Day",
      "description": null
    }
  ]
}
