{
  "month": "feb",
  "day": 17,
  "holidays": [
    {
      "title": "National Random Acts of Kindness Day",
      "description": null
    },
    {
      "title": "Analog to Digital TV Day",
      "description": null
    },
    {
      "title": "Angola Carnival Day",
      "description": null
    },
    {
      "title": "Brazilian Carninval",
      "description": null
    },
    {
      "title": "Champion Crab Races Day",
      "description": null
    },
    {
      "title": "Chinese Lunar New Year&#39;s Day",
      "description": null
    },
    {
      "title": "Chinese New Year",
      "description": null
    },
    {
      "title": "Chinese Spring Festival",
      "description": null
    },
    {
      "title": "Ecuador Carnival",
      "description": null
    },
    {
      "title": "Fasnacht Day",
      "description": null
    },
    {
      "title": "February 17th Revolution",
      "description": null
    },
    {
      "title": "Korean New Year",
      "description": null
    },
    {
      "title": "Kosovo Independence Day",
      "description": null
    },
    {
      "title": "Libyan Revolution Day",
      "description": null
    },
    {
      "title": "My Way Day",
      "description": null
    },
    {
      "title": "National Cabbage Day",
      "description": null
    },
    {
      "title": "National Cafe au Lait Day",
      "description": null
    },
    {
      "title": "National Public Science Day",
      "description": null
    },
    {
      "title": "National Tennis Pro Day",
      "description": null
    },
    {
      "title": "Seollal",
      "description": null
    },
    {
      "title": "Simplot Games",
      "description": null
    },
    {
      "title": "Tet Eve",
      "description": null
    },
    {
      "title": "Tet Holiday",
      "description": null
    },
    {
      "title": "Tet Nguyen Dan",
      "description": null
    },
    {
      "title": "Travel Africa Day",
      "description": null
    },
    {
      "title": "Who Shall I Be Day",
      "description": null
    },
    {
      "title": "World Human Spirit Day",
      "description": null
    }
  ]
}
